MANIFEST.in
setup.py
Fom.egg-info/PKG-INFO
Fom.egg-info/SOURCES.txt
Fom.egg-info/dependency_links.txt
Fom.egg-info/requires.txt
Fom.egg-info/top_level.txt
bin/fdbc
bin/reset_test_policies
docs/api.rst
docs/community.rst
docs/conf.py
docs/fdbc.rst
docs/fluiddb.rst
docs/index.rst
docs/objects.rst
docs/quickstart.rst
docs/_static/fom_logo.png
docs/_static/fom_lpbrand.png
docs/_static/fom_lpicon.png
docs/_static/fom_lplogo.png
docs/draco/README.rst
docs/draco/static/bblogo.png
docs/draco/static/draco.css
examples/objectmapping.py
examples/tag_collections.py
examples/ibd_study/__init__.py
examples/ibd_study/model.py
fom/__init__.py
fom/api.py
fom/db.py
fom/dev.py
fom/errors.py
fom/mapping.py
fom/session.py
fom/tx.py
fom/utils.py
fom/version.py
tests/__init__.py
tests/_base.py
tests/test_api.py
tests/test_base.py
tests/test_db.py
tests/test_errors.py
tests/test_integration.py
tests/test_mapping.py
tests/test_tx.py
tests/test_utils.py