Metadata-Version: 1.0
Name: Fom
Version: 0.9.10
Summary: FluidDB API and Object Mapper
Home-page: http://packages.python.org/Fom/
Author: Ali Afshar
Author-email: aafshar@gmail.com
License: UNKNOWN
Platform: UNKNOWN
